zword/__init__.py
zword/title2word.py
zword-0.0.4.data/scripts/wiki_txt
zword-0.0.4.dist-info/LICENSE
zword-0.0.4.dist-info/METADATA
zword-0.0.4.dist-info/WHEEL
zword-0.0.4.dist-info/top_level.txt
zword-0.0.4.dist-info/zip-safe
zword-0.0.4.dist-info/RECORD
