Metadata-Version: 2.1
Name: zword
Version: 0.0.4
Summary: 从维基百科抽取中文语料
Home-page: https://gitee.com/znlp/zword
Author: zuroc
Author-email: zsp042@gmail.com
License: UNKNOWN
Platform: UNKNOWN
Requires-Dist: zd
Requires-Dist: tqdm
Requires-Dist: gensim
Requires-Dist: opencc
Requires-Dist: fire
